xtrain/__init__.py
xtrain/base_trainer.py
xtrain/closure.py
xtrain/loss.py
xtrain/strategy.py
xtrain/utils.py
xtrain-0.4.3.dist-info/LICENSE
xtrain-0.4.3.dist-info/METADATA
xtrain-0.4.3.dist-info/WHEEL
xtrain-0.4.3.dist-info/RECORD
