Metadata-Version: 2.1
Name: xtrain
Version: 0.4.3
Summary: A Flax trainer
Author: Ji Yu
Author-email: jyu@uchc.edu
Requires-Python: >=3.10,<4.0
Classifier: Programming Language :: Python :: 3
Classifier: Programming Language :: Python :: 3.10
Classifier: Programming Language :: Python :: 3.11
Classifier: Programming Language :: Python :: 3.12
Classifier: Programming Language :: Python :: 3.13
Provides-Extra: cuda12
Requires-Dist: flax (>0.8)
Requires-Dist: jax[cuda12] (>=0.4,<0.5) ; extra == "cuda12"
